annaPack1/__init__.py
annaPack1/funcs.py
annaPack1-0.0.1.dist-info/METADATA
annaPack1-0.0.1.dist-info/WHEEL
annaPack1-0.0.1.dist-info/top_level.txt
annaPack1-0.0.1.dist-info/RECORD
