Metadata-Version: 2.1
Name: annaPack1
Version: 0.0.1
Summary: Python package for Adserver team in Kitech
Author: Nahyeon An
Author-email: anna@kitech.re.kr
Classifier: Programming Language :: Python :: 3
Classifier: License :: OSI Approved :: MIT License
Classifier: Operating System :: OS Independent
Requires-Python: >=3.6
Requires-Dist: numpy (>=1.20.0)
Requires-Dist: scipy (>=1.5.0)
Requires-Dist: matplotlib (>=3.0.0)
